{"page":181,"list":[{"id":"vO-n7X4IVg4","title":"SOTU Audience Gets Riled-Up When Biden's Talks About Medicare and Social Security","duration":164,"channel":{"name":"TIME","id":"UC8Su5vZCXWRag13H53zWVwA"}},{"id":"nce9VTthdgE","title":"Hockey Player Won't Wear The Pride Jersey","duration":188,"channel":{"name":"TheDC Shorts","id":"UCfDdlNLRVb1h3_7Xh-WhL3w"}},{"id":"IqH08pC6P2Y","title":"What does it mean to have a reprobate mind?  |  GotQuestions.org","duration":160,"channel":{"name":"Got Questions Ministries","id":"UCrHADU8H0P2Q_79sAhYjlGA"}},{"id":"l28SAdzkD_k","title":"The Midnight Air","duration":110,"channel":{"name":"2 Years Apart","id":"UCD3rJ108ouQzYIsvACKzMug"}},{"id":"RG7xhxP0tWQ","title":"The Itchyworms - Ayokong Tumanda (Live at Solenad)","duration":274,"channel":{"name":"The Itchyworms","id":"UC2yJMDPXcUl-8LGw7zsceeQ"}},{"id":"BwXjg47r-HU","title":"PAINT Trailer (2023) Owen Wilson","duration":94,"channel":{"name":"ONE Media","id":"UCzcRQ3vRNr6fJ1A9rqFn7QA"}},{"id":"Rhyk3lsABVs","title":"Half-Pound Kitten Takes Naps Under 130-Pound Dog | The Dodo Foster Diaries","duration":200,"channel":{"name":"The Dodo","id":"UCINb0wqPz-A0dV9nARjJlOQ"}},{"id":"dLlLxzU1Mbo","title":"SpaceX Super Heavy 31 Engine Static Fire [Slo Mo 4K]","duration":166,"channel":{"name":"Everyday Astronaut","id":"UC6uKrU_WqJ1R2HMTY3LIx5Q"}},{"id":"rzuUOqABGf0","title":"The Super Mario Bros Movie - Official Plumbing Commercial (2023) Chris Pratt, Charlie Day","duration":31,"channel":{"name":"IGN","id":"UCKy1dAqELo0zrOtPkf0eTMw"}},{"id":"yFwoHmg0atc","title":"The Most Dangerous Kitten Attacks Again","duration":217,"channel":{"name":"PawMeow","id":"UCs5Xl6fL6c4USxyEDSv-PXQ"}},{"id":"41G7pRmKbaQ","title":"Regretful granny succumbs to cancer 7 months after granddaughter’s tragic death","duration":259,"channel":{"name":"South China Morning Post","id":"UC4SUWizzKc1tptprBkWjX2Q"}},{"id":"mmDJXOWa5aQ","title":"BREAKING: High-altitude object shot down over Lake Huron, officials confirm to ABC News","duration":126,"channel":{"name":"ABC 7 Chicago","id":"UC_vFLohxs5PkAxlk7Y6jEtw"}},{"id":"hvL1339luv0","title":"Never gonna Meow you up","duration":61,"channel":{"name":"Rapid Liquid","id":"UC38r7_x7oMPAZweB2fvGDXQ"}},{"id":"9vwaD9cHLNw","title":"The Flash – Official Trailer","duration":177,"channel":{"name":"DC","id":"UCiifkYAs_bq1pt_zbNAzYGg"}},{"id":"JqcncLPi9zw","title":"Marvel Studios’ Guardians of the Galaxy Vol. 3 | New Trailer","duration":142,"channel":{"name":"Marvel Entertainment","id":"UCvC4D8onUfXzvjTOM-dBfEA"}},{"id":"WFKXJ091Ed4","title":"Chris Stapleton Sings the National Anthem at Super Bowl LVII","duration":146,"channel":{"name":"NFL","id":"UCDVYQ4Zhbm3S2dlz7P1GBDg"}},{"id":"M7bv49ugGik","title":"Stray Cat Shows Up At Fire Station And Moves Right In With Firefighters | The Dodo","duration":202,"channel":{"name":"The Dodo","id":"UCINb0wqPz-A0dV9nARjJlOQ"}},{"id":"q-7S1j4b3vY","title":"The Chiefs bar that won't be open on Super Bowl Sunday 🤯","duration":226,"channel":{"name":"NFL on ESPN","id":"UCiio0ydw439X13KyZgMIcHw"}},{"id":"ZzH_qo8v7Yo","title":"Mild Super Bowl Sunday","duration":213,"channel":{"name":"KOAT","id":"UC41xJSNY2xCPC4-gOsRcDcg"}}],"totalPages":182}