{"page":3,"list":[{"id":"c0rxuDdvArs","title":"Broke College Kids Try Each Other's Ramen","duration":460,"channel":{"name":"Cocoa Butter","id":"UCcOWHZl_mlhs2Yjo9Lyhb7g"}},{"id":"-80FjBQ57hk","title":"NBA celebrations but they get increasingly more cold","duration":482,"channel":{"name":"CoshReport","id":"UCOIaQxIvcpPjxgSaYmqaE6g"}},{"id":"AnIOJoiU4bs","title":"Woman raised this bird like a baby. Now he's 50 years old.","duration":291,"channel":{"name":"GeoBeats Animals","id":"UC7_VH_kj0aD9vhuHmFheUYQ"}},{"id":"tSUURvSBR-4","title":"Lion's Mane Mushrooms Actually DO SOMETHING!","duration":374,"channel":{"name":"SciShow","id":"UCZYTClx2T1of7BRZ86-8fow"}},{"id":"DCHbhDxBLko","title":"How Your Childhood Influence The Way You Express Love (love styles)","duration":392,"channel":{"name":"Psych2Go","id":"UCkJEpR7JmS36tajD34Gp4VA"}},{"id":"nzXXLBNWzKo","title":"NBA 0 IQ Moments","duration":489,"channel":{"name":"dime","id":"UCpyoYVlp67N16Lg1_N4VnVw"}},{"id":"ZWFiD5-hhFU","title":"The Newest Chapters in the Pokémon Series 📔 | Pokémon Scarlet and Pokémon Violet","duration":236,"channel":{"name":"The Official Pokémon YouTube channel","id":"UCFctpiB_Hnlk3ejWfHqSm6Q"}},{"id":"X0c6NhIpRos","title":"CAVALIERS at LAKERS | NBA FULL GAME HIGHLIGHTS | November 6, 2022","duration":567,"channel":{"name":"NBA","id":"UCWJ2lWNubArHWmf3FIHbfcQ"}},{"id":"YLLsD7Vedm8","title":"Ukraine War: Russia losing aircraft faster than they can replace them","duration":230,"channel":{"name":"Sky News","id":"UCoMdktPbSTixAyNGwb-UYkQ"}},{"id":"amrhqGOOkyA","title":"I Became A Math Teacher For A Day!","duration":531,"channel":{"name":"MsMunchie","id":"UCc-WbFxYCQUdFkgEuJF19zw"}},{"id":"vrAH-yJiAU4","title":"Drawing for $1.9 billion Powerball jackpot delayed","duration":50,"channel":{"name":"ABC7","id":"UCVxBA3Cbu3pm8w8gEIoMEog"}},{"id":"Ekui3tG3Dy4","title":"When \"Asian\" is a Difficulty Mode 2","duration":308,"channel":{"name":"Steven He","id":"UCP0_k4INXrwPS6HhIyYqsTg"}},{"id":"TbOpGn_CrEU","title":"Actual Footage of my dad's Trip to School","duration":160,"channel":{"name":"Steven He","id":"UCP0_k4INXrwPS6HhIyYqsTg"}},{"id":"k0eHQe2KY3U","title":"400ft Tall Halloween Light and Drone Show! Featuring: Metallica, Stranger Things, and Ghostbusters","duration":520,"channel":{"name":"Tom BetGeorge","id":"UC7MpCYgKuthAMTZxQTeYV5g"}},{"id":"B5WUhJUog_M","title":"iPhone Vs 8000 Feet Drop!","duration":565,"channel":{"name":"Beast Reacts","id":"UCUaT_39o1x6qWjz7K2pWcgw"}},{"id":"Hs8buls4cos","title":"EXPENSIVE FAILS","duration":495,"channel":{"name":"Hooked","id":"UCX7-9i_uq-HjLHbRJiMwEng"}},{"id":"fIdRWKel0xQ","title":"The Problem with New York City..","duration":434,"channel":{"name":"CaseyNeistat","id":"UCtinbF-Q-fVthA0qrFQTgXQ"}},{"id":"ZcrMmCbn_yg","title":"Brewstew - The One Chip Challenge","duration":353,"channel":{"name":"brewstewfilms","id":"UCepPGz8AVCbggMl3BvboaBA"}},{"id":"Xh2TY0DMbas","title":"I Survived Sensory Deprivation","duration":495,"channel":{"name":"Ryan Trahan","id":"UCnmGIkw-KdI0W5siakKPKog"}},{"id":"LLyXxB0bgNg","title":"Horrors Behind the Scenes of the Wizard of Oz","duration":552,"channel":{"name":"Facts Verse","id":"UCXZpQgX1897wYDLtvzmgyIA"}}],"totalPages":8}