{"page":56,"list":[{"id":"-XYT9MyAEFs","title":"Herschel Walker Cold Open - SNL","duration":293,"channel":{"name":"Saturday Night Live","id":"UCqFzWxSCi39LnW1JKFR3efg"}},{"id":"yVmJI9OrnGk","title":"ABC Alphabet Song | Nursery Rhymes & Kids Songs | قناة وناسة - Super Renell","duration":140,"channel":{"name":"Super Renell - Kids Songs","id":"UC7JKloC8ELKQS1hE_PhhWSw"}},{"id":"TWSF3df6jUs","title":"The giant water lily is VICIOUS! 😱 The Green Planet  🌱BBC","duration":212,"channel":{"name":"BBC","id":"UCCj956IF62FbT7Gouszaj9w"}},{"id":"XXYxZySYeFU","title":"Fortnite Chapter 4 Season 1 Launch Trailer","duration":96,"channel":{"name":"Fortnite","id":"UClG8odDC8TS6Zpqk9CGVQiQ"}},{"id":"Nr9wqwIIPnU","title":"Takeoff's Alleged Killer caught another body in 2018 but wasnt charged when Someone Tried to Rob Him","duration":220,"channel":{"name":"DJ Akademiks","id":"UCs06q9pyRn8d8xy0NgzKPrA"}},{"id":"m7kqBQyUAGQ","title":"Chuck Todd: Donald Trump’s 2024 Campaign Is ‘Catastrophic Failure’ So Far","duration":299,"channel":{"name":"NBC News","id":"UCeY0bbntWzzVIaj2z3QigXg"}},{"id":"3sloRjKLkUQ","title":"Spring family followed home almost 30 miles","duration":127,"channel":{"name":"KPRC 2 Click2Houston","id":"UCKQECjul8nw1KW_JzfBTP1A"}},{"id":"UpF64xyNPrQ","title":"Just The Two Of Us - Marcin and Ichika Nito","duration":124,"channel":{"name":"Marcin","id":"UCZiGGE0e0DctISlShAILbjQ"}},{"id":"nO_OaPOTtz0","title":"Man brings home two cats. Then one of them started disrespecting gravity.","duration":194,"channel":{"name":"GeoBeats Animals","id":"UC7_VH_kj0aD9vhuHmFheUYQ"}},{"id":"S2MbnYO2Xyw","title":"r/Minecraft just said something unforgivable. You need to see it to believe it.","duration":236,"channel":{"name":"Phoenix SC","id":"UCj4zC1Hfj-uc90FUXzRamNw"}},{"id":"DuWEEKeJLMI","title":"Cocaine Bear | Official Trailer [HD]","duration":140,"channel":{"name":"Universal Pictures","id":"UCq0OueAsdxH6b8nyAspwViw"}},{"id":"ANbBcsr8wPc","title":"10-Year-Old Boy Allegedly Killed Mom Over Amazon Purchase","duration":65,"channel":{"name":"Inside Edition","id":"UC9k-yiEpRHMNVOnOi_aQK8w"}},{"id":"iWyMcy4_alQ","title":"For Spanish, Press \"2\" | Gabriel Iglesias","duration":260,"channel":{"name":"Gabriel Iglesias","id":"UCUxc0iEpV8wZV4WLOui0RwQ"}},{"id":"UcnEc61SJ64","title":"France vs. Poland Highlights | 2022 FIFA World Cup | Round of 16","duration":294,"channel":{"name":"FOX Soccer","id":"UCooTLkxcpnTNx6vfOovfBFA"}},{"id":"ldmFHNJmw6w","title":"When you accidentally write songs that already exist part 4","duration":292,"channel":{"name":"Daniel Thrasher","id":"UCnZx--LpG2spgmlxOcC-DRA"}},{"id":"tqVeYOXEAGk","title":"Volkor X feat. DrDisrespect - Another Way (Official Audio)","duration":284,"channel":{"name":"Volkor X","id":"UC96adbHcemouoJCI024LPDQ"}},{"id":"Nt3kzGd647Q","title":"Steps - Heartbeat (Behind the Scenes)","duration":125,"channel":{"name":"StepsOfficial","id":"UCLEssuRup7N5Jopd4dMCScQ"}},{"id":"alNLBiOlF4U","title":"Ready","duration":78,"channel":{"name":"Anywhere on Earth","id":"UCyWWQkBVP-PQfLUMQV4bIMA"}},{"id":"9uU7HqqEoMQ","title":"Sweetest dog had a sad start to life. Then he discovered love and massages.","duration":168,"channel":{"name":"GeoBeats Animals","id":"UC7_VH_kj0aD9vhuHmFheUYQ"}},{"id":"eiE7GNkr9Uo","title":"Polar Bear Purrs When Cuddling with Her Human Dad","duration":218,"channel":{"name":"Animal Planet","id":"UCkEBDbzLyH-LbB2FgMoSMaQ"}}],"totalPages":86}