{"page":180,"list":[{"id":"FSkbKKtBF5s","title":"Tucker: The FBI has joined the hunt for Christians","duration":221,"channel":{"name":"Fox News","id":"UCXIJgqnII2ZOINSWNOGFThA"}},{"id":"w1G-ThTMFU8","title":"U.S. fighter jet shot down unidentified object in northern Canada","duration":175,"channel":{"name":"NBC News","id":"UCeY0bbntWzzVIaj2z3QigXg"}},{"id":"qNYNoC7RM4Q","title":"i can play anything by ear","duration":239,"channel":{"name":"Daniel Thrasher","id":"UCnZx--LpG2spgmlxOcC-DRA"}},{"id":"LEqMFCFSbSc","title":"Extremely Needy Golden Retriever Meets Dad's New Girlfriend | The Dodo Soulmates","duration":185,"channel":{"name":"The Dodo","id":"UCINb0wqPz-A0dV9nARjJlOQ"}},{"id":"Yc3BQCsEiDI","title":"Air On G Sting","duration":185,"channel":{"name":"2 Years Apart","id":"UCD3rJ108ouQzYIsvACKzMug"}},{"id":"BoTVJvvXNnc","title":"Parade","duration":194,"channel":{"name":"YOUNHA OFFICIAL","id":"UCmAT2nOQB0ofAhlc7_2P8GA"}},{"id":"idKZTWrtgl0","title":"Chinese satellite lasers recorded over Hawaii","duration":175,"channel":{"name":"KHON2 News","id":"UCtqFUxpLnV-RaraQVu1rMTw"}},{"id":"KFw2R3orkro","title":"Kyrie Irving & Luka Doncic 1st Game Together 🔥 55 Points Combined Highlights","duration":179,"channel":{"name":"House of Highlights","id":"UCqQo7ewe87aYAe7ub5UqXMw"}},{"id":"EMD4WVw7x_Y","title":"Islam Makhachev Octagon Interview | UFC 284","duration":186,"channel":{"name":"UFC - Ultimate Fighting Championship","id":"UCvgfXK4nTYKudb0rFR6noLA"}},{"id":"w-P1co1HSYc","title":"Alexander Volkanovski Octagon Interview | UFC 284","duration":158,"channel":{"name":"UFC - Ultimate Fighting Championship","id":"UCvgfXK4nTYKudb0rFR6noLA"}},{"id":"PBbSfrOKHxw","title":"High-altitude object shot down over northern Canada, Montana airspace temporarily closed","duration":125,"channel":{"name":"6abc Philadelphia","id":"UCw77677G3EAODp61b0izs7w"}},{"id":"iKUJhg5GLNU","title":"Baton Twirling Like You've Never Seen Before - Hilarious and Unexpected","duration":175,"channel":{"name":"Michelle Christa Smith","id":"UC-Z8eTFtiyP88XylvO-lBHw"}},{"id":"q7i9__V9RCU","title":"Shannon Sharpe Pulled Skip Bayless Aside to Mend Their Relationship","duration":268,"channel":{"name":"SiriusXM","id":"UC49ta0RHXJUiID5KWRkcySw"}},{"id":"_zB4rscrbI4","title":"Lifelong Chiefs fan writes 'Twas the Night Before the Super Bowl' poem","duration":111,"channel":{"name":"KMBC 9","id":"UCWTkpYvniGIUe1jeCncFzKw"}},{"id":"jCupXEP-4LI","title":"Feral Senior Cat Becomes A Total Mama's Boy - MR. BELVEDERE | The Dodo","duration":216,"channel":{"name":"The Dodo","id":"UCINb0wqPz-A0dV9nARjJlOQ"}},{"id":"sHA-IwY3LaI","title":"Underwater Pizza Delivery","duration":204,"channel":{"name":"Daily Dose Of Internet","id":"UCdC0An4ZPNr_YiFiYoVbwaw"}},{"id":"NquvhHIkQqk","title":"Chocolate Drip","duration":144,"channel":{"name":"The Good Time Girls","id":"UCHojJOmFfNYofMmgumEb5og"}},{"id":"lm_Ozw6izg0","title":"The story behind viral video of barber and young client with Down syndrome l GMA","duration":247,"channel":{"name":"Good Morning America","id":"UCH1oRy1dINbMVp3UFWrKP0w"}},{"id":"FbvCphKD3ro","title":"14-Year-Old Golden Retriever Brings Surprises to Neighbors Every Day | The Dodo","duration":223,"channel":{"name":"The Dodo","id":"UCINb0wqPz-A0dV9nARjJlOQ"}},{"id":"5GHPYlHtXkc","title":"Inside Look at This Year’s Super Bowl Security Measures","duration":115,"channel":{"name":"Inside Edition","id":"UC9k-yiEpRHMNVOnOi_aQK8w"}}],"totalPages":182}