{"page":87,"list":[{"id":"yp-9HwHijwI","title":"\"I'm Wearing A Mic Better Be Careful What You Say\" Referee To Kailer Yamamoto","duration":59,"channel":{"name":"Jens95","id":"UCA3Lillszhzs_Mv0Da0EHlg"}},{"id":"zOPtm1-VAPs","title":"Jets crowd is fed up with Zach Wilson after 3 point half","duration":135,"channel":{"name":"Highlight Heaven","id":"UCq0grzC77X9UZd9xngQRTjg"}},{"id":"nc8neFqI9vA","title":"Holocaust survivor recalls the first time she met US Army officer, who later to became her husband","duration":141,"channel":{"name":"Yad Vashem","id":"UCMIWdcUSEHSIGgTEgT5fU4g"}},{"id":"TmkAfRSjnm0","title":"Student Accepted to Every Ivy League School Chooses to Attend None of Them","duration":98,"channel":{"name":"ABC News","id":"UCBi2mrWuNuyYy4gbM6fU18Q"}},{"id":"zhYoCdDvPu8","title":"Hundreds of flights canceled at Sea-Tac Airport | FOX 13 Seattle","duration":185,"channel":{"name":"FOX 13 Seattle","id":"UC5bKZHg4PzURMOWcvanl6nA"}},{"id":"hbe1CoNnUQg","title":"Freezing temperatures causing major power outages | GMA","duration":201,"channel":{"name":"ABC News","id":"UCBi2mrWuNuyYy4gbM6fU18Q"}}],"totalPages":88}